dddify/__init__.py
dddify/__main__.py
dddify/cli.py
dddify/config.py
dddify/service.py
dddify/utils.py
dddify/templates/aggregate.py.j2
dddify/templates/application_services.py.j2
dddify/templates/commands.py.j2
dddify/templates/container.py.j2
dddify/templates/create_command.py.j2
dddify/templates/di_init.py.j2
dddify/templates/domain_init.py.j2
dddify/templates/entities.py.j2
dddify/templates/entities_init.py.j2
dddify/templates/events.py.j2
dddify/templates/exception_handlers.py.j2
dddify/templates/exceptions.py.j2
dddify/templates/get_query.py.j2
dddify/templates/orm.py.j2
dddify/templates/persistence_init.py.j2
dddify/templates/ports.py.j2
dddify/templates/ports_file.py.j2
dddify/templates/presentation_init.py.j2
dddify/templates/queries.py.j2
dddify/templates/repository.py.j2
dddify/templates/router.py.j2
dddify/templates/schemas.py.j2
dddify/templates/service.py.j2
dddify/templates/value_objects.py.j2
dddify-0.1.1.dist-info/METADATA
dddify-0.1.1.dist-info/WHEEL
dddify-0.1.1.dist-info/entry_points.txt
dddify-0.1.1.dist-info/RECORD
