Metadata-Version: 2.4
Name: dddify
Version: 0.1.1
Summary: DDD Structure Generator for Python Projects
Project-URL: Homepage, https://github.com/mathisarends/dddify
Project-URL: Repository, https://github.com/mathisarends/dddify
Author-email: Mathis <mathisarends27@gmail.com>
License: MIT
Keywords: code-generator,ddd,domain-driven-design,fastapi
Classifier: Development Status :: 3 - Alpha
Classifier: Intended Audience :: Developers
Classifier: Programming Language :: Python :: 3.11
Classifier: Programming Language :: Python :: 3.12
Classifier: Programming Language :: Python :: 3.13
Classifier: Topic :: Software Development :: Code Generators
Requires-Python: >=3.11
Requires-Dist: jinja2>=3.1.6
Requires-Dist: rich>=14.3.1
Requires-Dist: typer>=0.21.1
